cranial/connectors/__init__.py
cranial/connectors/base.py
cranial/connectors/googlecloudstorage.py
cranial/connectors/http.py
cranial/connectors/local.py
cranial/connectors/s3.py
cranial/datastore/adapters/cassandra.py
cranial/datastore/adapters/psql.py
cranial/datastore/dbapi.py
cranial/fetcher.py
cranial/fetchers.py
cranial/keyvalue/README.rst
cranial/keyvalue/__init__.py
cranial/keyvalue/interceptor.py
cranial/keyvalue/keyvalue.py
cranial/keyvalue/kvandra.py
cranial_datastore-0.3.3.dist-info/LICENSE
cranial_datastore-0.3.3.dist-info/WHEEL
cranial_datastore-0.3.3.dist-info/METADATA
cranial_datastore-0.3.3.dist-info/RECORD
