Metadata-Version: 2.1
Name: cranial-datastore
Version: 0.3.3
Summary: Data storage connectivity & utilities for Cranial.
Home-page: https://github.com/tribune/cranial-datastore
License: GPL-3.0+
Author: Matt Chapman et al.
Author-email: Matt@NinjitsuWeb.com
Requires-Python: >=3.5
Classifier: License :: OSI Approved :: GNU General Public License v3 or later (GPLv3+)
Classifier: Programming Language :: Python :: 3
Classifier: Programming Language :: Python :: 3.5
Classifier: Programming Language :: Python :: 3.6
Classifier: Programming Language :: Python :: 3.7
Requires-Dist: boto3 (>=1.9,<2.0)
Requires-Dist: cachetools (>=2.1,<3.0)
Requires-Dist: cranial-common (>=0.2.0,<0.3.0)
